amap_holydragon/__init__.py
amap_holydragon/amap.py
amap_holydragon/main.py
amap_holydragon-1.0.3.dist-info/LICENSE
amap_holydragon-1.0.3.dist-info/METADATA
amap_holydragon-1.0.3.dist-info/WHEEL
amap_holydragon-1.0.3.dist-info/entry_points.txt
amap_holydragon-1.0.3.dist-info/top_level.txt
amap_holydragon-1.0.3.dist-info/RECORD
